datadreamer/__init__.py
datadreamer/dataset_annotation/__init__.py
datadreamer/dataset_annotation/aimv2_annotator.py
datadreamer/dataset_annotation/clip_annotator.py
datadreamer/dataset_annotation/cls_annotator.py
datadreamer/dataset_annotation/image_annotator.py
datadreamer/dataset_annotation/owlv2_annotator.py
datadreamer/dataset_annotation/sam2_annotator.py
datadreamer/dataset_annotation/slimsam_annotator.py
datadreamer/dataset_annotation/utils.py
datadreamer/image_generation/__init__.py
datadreamer/image_generation/clip_image_tester.py
datadreamer/image_generation/image_generator.py
datadreamer/image_generation/sdxl_image_generator.py
datadreamer/image_generation/sdxl_lightning_image_generator.py
datadreamer/image_generation/sdxl_turbo_image_generator.py
datadreamer/image_generation/shuttle_3_image_generator.py
datadreamer/pipelines/__init__.py
datadreamer/pipelines/generate_dataset_from_scratch.py
datadreamer/prompt_generation/__init__.py
datadreamer/prompt_generation/lm_prompt_generator.py
datadreamer/prompt_generation/lm_synonym_generator.py
datadreamer/prompt_generation/profanity_filter.py
datadreamer/prompt_generation/prompt_generator.py
datadreamer/prompt_generation/qwen2_lm_prompt_generator.py
datadreamer/prompt_generation/simple_prompt_generator.py
datadreamer/prompt_generation/synonym_generator.py
datadreamer/prompt_generation/tinyllama_lm_prompt_generator.py
datadreamer/prompt_generation/wordnet_synonym_generator.py
datadreamer/utils/__init__.py
datadreamer/utils/bad_words.py
datadreamer/utils/base_converter.py
datadreamer/utils/coco_converter.py
datadreamer/utils/config.py
datadreamer/utils/convert_dataset.py
datadreamer/utils/dataset_utils.py
datadreamer/utils/luxonis_dataset_converter.py
datadreamer/utils/merge_raw_datasets.py
datadreamer/utils/nms.py
datadreamer/utils/single_label_cls_converter.py
datadreamer/utils/voc_converter.py
datadreamer/utils/yolo_converter.py
datadreamer-0.2.2.dist-info/licenses/LICENSE
examples/image_annotation_example.py
examples/image_generation_example.py
datadreamer-0.2.2.dist-info/METADATA
datadreamer-0.2.2.dist-info/WHEEL
datadreamer-0.2.2.dist-info/entry_points.txt
datadreamer-0.2.2.dist-info/top_level.txt
datadreamer-0.2.2.dist-info/RECORD
