Metadata-Version: 2.4
Name: datadreamer
Version: 0.2.2
Summary: A library for dataset generation and knowledge extraction from foundation computer vision models.
Maintainer-email: Luxonis <support@luxonis.com>
License:                                  Apache License
Project-URL: Homepage, https://github.com/luxonis/datadreamer
Keywords: computer vision,AI,machine learning,generative models
Classifier: License :: OSI Approved :: Apache Software License
Classifier: Development Status :: 3 - Alpha
Classifier: Programming Language :: Python :: 3.8
Classifier: Intended Audience :: Developers
Classifier: Topic :: Software Development :: Libraries
Classifier: Topic :: Scientific/Engineering :: Artificial Intelligence
Classifier: Topic :: Scientific/Engineering :: Image Processing
Classifier: Topic :: Scientific/Engineering :: Image Recognition
Requires-Python: >=3.8
License-File: LICENSE
Requires-Dist: torch>=2.6.0
Requires-Dist: torchvision>=0.16.0
Requires-Dist: transformers>=4.45.2
Requires-Dist: diffusers>=0.31.0
Requires-Dist: compel>=2.0.0
Requires-Dist: tqdm>=4.0.0
Requires-Dist: Pillow>=9.0.0
Requires-Dist: numpy>=1.22.0
Requires-Dist: matplotlib>=3.6.0
Requires-Dist: opencv-python>=4.7.0
Requires-Dist: accelerate>=0.25.0
Requires-Dist: scipy>=1.10.0
Requires-Dist: bitsandbytes>=0.42.0
Requires-Dist: nltk>=3.8.1
Requires-Dist: luxonis-ml[data,utils]==0.8.0
Requires-Dist: python-box>=7.1.1
Requires-Dist: gcsfs>=2023.1.0
Requires-Dist: sentencepiece>=0.2.0
Requires-Dist: optimum-quanto>=0.2.6
Requires-Dist: huggingface_hub>=0.28.1
Requires-Dist: loguru>=0.7.0
Requires-Dist: pycocotools>=2.0.7
Requires-Dist: sam2>=1.1.0
Provides-Extra: dev
Requires-Dist: pre-commit>=3.2.1; extra == "dev"
Requires-Dist: toml>=0.10.2; extra == "dev"
Dynamic: license-file
